[{"code":"005979","name":"南方合顺多资产(FOF)A","fromThisYear":"4.58","recent1Week":"0.44","recent1Month":"1.6","recent3Month":"2.72","recent6Month":"5.4","recent1Year":"0.15","recent2Year":"-5.67","recent3Year":"-12.3","day":"2024-07-11","unitNetWorth":"1.3797","rank1Week":70,"rank1Month":10,"rank3Month":7,"rank6Month":12,"rank1Year":113,"rank2Year":140,"rank3Year":70,"rankFromBuild":70,"totalFunds":844},{"code":"005980","name":"南方合顺多资产(FOF)C","fromThisYear":"4.36","recent1Week":"0.44","recent1Month":"1.57","recent3Month":"2.62","recent6Month":"5.19","recent1Year":"-0.24","recent2Year":"-6.43","recent3Year":"-13.35","day":"2024-07-11","unitNetWorth":"1.3497","rank1Week":77,"rank1Month":11,"rank3Month":8,"rank6Month":21,"rank1Year":134,"rank2Year":150,"rank3Year":77,"rankFromBuild":77,"totalFunds":844},{"code":"007272","name":"景顺稳健养老目标三年混合(FOF)A","fromThisYear":"1.69","recent1Week":"0.33","recent1Month":"0.15","recent3Month":"0.83","recent6Month":"2.55","recent1Year":"0.21","recent2Year":"-0.21","recent3Year":"-9.03","day":"2024-07-11","unitNetWorth":"1.1189","rank1Week":62,"rank1Month":137,"rank3Month":142,"rank6Month":172,"rank1Year":109,"rank2Year":42,"rank3Year":62,"rankFromBuild":62,"totalFunds":844}]